mak/gnuoy/utils/config.py
mak.gnuoy_python_utils-0.1.0.dist-info/LICENSE
mak.gnuoy_python_utils-0.1.0.dist-info/METADATA
mak.gnuoy_python_utils-0.1.0.dist-info/WHEEL
mak.gnuoy_python_utils-0.1.0.dist-info/top_level.txt
mak.gnuoy_python_utils-0.1.0.dist-info/RECORD
