Metadata-Version: 2.1
Name: mak.gnuoy-python-utils
Version: 0.1.0
Summary: mak.gnuoy's python utilities package
Author-email: Mak Gnuoy <mak.gnuoy@gmail.com>
Project-URL: Homepage, https://github.com/mak-gnuoy/python-utils
Project-URL: Bug Tracker, https://github.com/mak-gnuoy/python-utils/issues
Classifier: Programming Language :: Python :: 3
Classifier: License :: OSI Approved :: MIT License
Classifier: Operating System :: OS Independent
Requires-Python: >=3.7
License-File: LICENSE
